{
 "SoundBanksInfo": {
  "Platform": "Windows",
  "BasePlatform": "Windows",
  "SchemaVersion": "16",
  "SoundBankVersion": "145",
  "RootPaths": {
   "ProjectRoot": "../..",
   "SourceFilesRoot": "../../.cache/Windows",
   "SoundBanksRoot": ".",
   "ExternalSourcesInputFile": "",
   "ExternalSourcesOutputRoot": "."
  },
  "DialogueEvents": [],
  "SoundBanks": [
   {
    "Id": "1355168291",
    "Type": "User",
    "GUID": "{701ECBBD-9C7B-4030-8CDB-749EE5D1C7B9}",
    "Language": "SFX",
    "Hash": "{55A8B452-780A-F354-2D4B-3DA7689F1752}",
    "ObjectPath": "Init",
    "ShortName": "Init",
    "Path": "Init.bnk",
    "Plugins": {
     "ShareSets": [
      {
       "Id": "48620415",
       "Name": "Have_U_Ever_Been_Outside",
       "ObjectPath": "\\Effects\\Factory Effects\\Wwise RoomVerb\\Exteriors\\Have_U_Ever_Been_Outside",
       "GUID": "{FE29AE8D-FD86-4652-A95D-68D32F5760EC}",
       "LibName": "Wwise RoomVerb",
       "LibId": "7733251"
      },
      {
       "Id": "3442768367",
       "Name": "Hall_Large_Dark",
       "ObjectPath": "\\Effects\\Factory Effects\\Wwise RoomVerb\\Halls\\Hall_Large_Dark",
       "GUID": "{0F6A7D6D-131C-4650-9561-FC05F5C7A37B}",
       "LibName": "Wwise RoomVerb",
       "LibId": "7733251"
      }
     ],
     "AudioDevices": [
      {
       "Id": "2317455096",
       "Name": "No_Output",
       "ObjectPath": "\\Audio Devices\\Default Work Unit\\No_Output",
       "GUID": "{7FE4E25A-DA85-4ED4-844F-FEF20822D3C6}",
       "LibName": "No Output",
       "LibId": "11862023"
      },
      {
       "Id": "3859886410",
       "Name": "System",
       "ObjectPath": "\\Audio Devices\\Default Work Unit\\System",
       "GUID": "{753FC237-F057-46EE-AEA6-CEB87F8AC746}",
       "LibName": "System",
       "LibId": "11403271"
      }
     ]
    },
    "Busses": [
     {
      "Id": "89505537",
      "Name": "Gameplay",
      "ObjectPath": "\\Master-Mixer Hierarchy\\Default Work Unit\\Master Audio Bus\\Gameplay",
      "GUID": "{35710773-A672-49E3-94CD-FEE992734CDD}"
     },
     {
      "Id": "3803692087",
      "Name": "Master Audio Bus",
      "ObjectPath": "\\Master-Mixer Hierarchy\\Default Work Unit\\Master Audio Bus",
      "GUID": "{1514A4D8-1DA6-412A-A17E-75CA0C2149F3}"
     }
    ],
    "AuxBusses": [
     {
      "Id": "3717191513",
      "Name": "OpenCave_Reverb",
      "ObjectPath": "\\Master-Mixer Hierarchy\\Default Work Unit\\Master Audio Bus\\Gameplay\\OpenCave_Reverb",
      "GUID": "{6C93671D-1FB3-4167-8C0E-D3BA1142FA69}",
      "PluginRefs": {
       "ShareSets": [
        {
         "Id": "48620415"
        }
       ]
      }
     },
     {
      "Id": "4263088964",
      "Name": "DeathWhisle_Reverb",
      "ObjectPath": "\\Master-Mixer Hierarchy\\Default Work Unit\\Master Audio Bus\\Gameplay\\DeathWhisle_Reverb",
      "GUID": "{2355226F-E4CB-4F1D-AB37-7842C4BAD5C0}",
      "PluginRefs": {
       "ShareSets": [
        {
         "Id": "3442768367"
        }
       ]
      }
     }
    ],
    "GameParameters": [
     {
      "Id": "215992295",
      "Name": "Player_Health",
      "ObjectPath": "\\Game Parameters\\Default Work Unit\\Player_Health",
      "GUID": "{076122B2-10D5-4975-8283-FB2CEF599DE9}"
     }
    ],
    "StateGroups": [
     {
      "Id": "1069431850",
      "Name": "Player",
      "ObjectPath": "\\States\\Default Work Unit\\Player",
      "GUID": "{87B4E536-9AE8-48BB-A0CF-8B42EF7E7C4E}",
      "States": [
       {
        "Id": "655265632",
        "Name": "Alive",
        "ObjectPath": "\\States\\Default Work Unit\\Player\\Alive",
        "GUID": "{46EF42CB-0A3A-4B30-9381-5009C43676DA}"
       },
       {
        "Id": "748895195",
        "Name": "None",
        "ObjectPath": "\\States\\Default Work Unit\\Player\\None",
        "GUID": "{2344529B-7E6C-4653-88D8-C07CCD441EEA}"
       },
       {
        "Id": "2044049779",
        "Name": "Dead",
        "ObjectPath": "\\States\\Default Work Unit\\Player\\Dead",
        "GUID": "{0536CE74-4099-4668-85B0-BC25C1594966}"
       }
      ]
     }
    ],
    "SwitchGroups": [
     {
      "Id": "1834394558",
      "Name": "Surface",
      "ObjectPath": "\\Switches\\Default Work Unit\\Surface",
      "GUID": "{DAA0AC4F-CD6C-4725-9736-F10D4275C9F1}",
      "Switches": [
       {
        "Id": "712897245",
        "Name": "Mud",
        "ObjectPath": "\\Switches\\Default Work Unit\\Surface\\Mud",
        "GUID": "{F56F098E-C950-4E09-9E48-305F3D9917D2}"
       },
       {
        "Id": "803837735",
        "Name": "Sand",
        "ObjectPath": "\\Switches\\Default Work Unit\\Surface\\Sand",
        "GUID": "{07261111-85DA-4848-9D5C-4590F83E2574}"
       },
       {
        "Id": "1216965916",
        "Name": "Stone",
        "ObjectPath": "\\Switches\\Default Work Unit\\Surface\\Stone",
        "GUID": "{81127D2F-33FA-4645-B673-AAE14C0A3834}"
       },
       {
        "Id": "2195636714",
        "Name": "Dirt",
        "ObjectPath": "\\Switches\\Default Work Unit\\Surface\\Dirt",
        "GUID": "{99AE1BB1-0840-4DA3-8906-184B4A011CBE}"
       },
       {
        "Id": "2654748154",
        "Name": "Water",
        "ObjectPath": "\\Switches\\Default Work Unit\\Surface\\Water",
        "GUID": "{B9EA5374-CA9F-4D4B-A504-D33B42796948}"
       }
      ]
     },
     {
      "Id": "3257506471",
      "Name": "Impact",
      "ObjectPath": "\\Switches\\Default Work Unit\\Impact",
      "GUID": "{F15315EE-20B4-4E71-A6F0-2E2ECBEA8B7A}",
      "Switches": [
       {
        "Id": "1216965916",
        "Name": "Stone",
        "ObjectPath": "\\Switches\\Default Work Unit\\Impact\\Stone",
        "GUID": "{21EFE8C6-1AF6-4D9A-8F2C-D46DBAAC54F8}"
       },
       {
        "Id": "2195636714",
        "Name": "Dirt",
        "ObjectPath": "\\Switches\\Default Work Unit\\Impact\\Dirt",
        "GUID": "{D63A2816-2BF5-4E43-96BF-92ADF5EFD709}"
       },
       {
        "Id": "2654748154",
        "Name": "Water",
        "ObjectPath": "\\Switches\\Default Work Unit\\Impact\\Water",
        "GUID": "{76A15951-554F-417A-B26F-034713D0CAB1}"
       }
      ]
     }
    ]
   },
   {
    "Id": "3161908922",
    "Type": "User",
    "GUID": "{CB266DD4-F623-48C5-AA10-E63E0D349C1D}",
    "Language": "SFX",
    "Hash": "{8B39F9E6-9022-7076-F860-5C44F97D161B}",
    "ObjectPath": "\\SoundBanks\\Default Work Unit\\Main",
    "ShortName": "Main",
    "Path": "Main.bnk",
    "Media": [
     {
      "Id": "13622979",
      "Language": "SFX",
      "Streaming": "false",
      "Location": "Memory",
      "ShortName": "Grunt_Hit-003.wav",
      "CachePath": "SFX/Grunt_Hit-003_10C4C929.wem"
     },
     {
      "Id": "31203274",
      "Language": "SFX",
      "Streaming": "false",
      "Location": "Memory",
      "ShortName": "Dirt_Impact.wav",
      "CachePath": "SFX/Dirt_Impact_10C4C929.wem"
     },
     {
      "Id": "33923621",
      "Language": "SFX",
      "Streaming": "false",
      "Location": "Memory",
      "ShortName": "FS_Dirt-003.wav",
      "CachePath": "SFX/FS_Dirt-003_10C4C929.wem"
     },
     {
      "Id": "75816713",
      "Language": "SFX",
      "Streaming": "false",
      "Location": "Memory",
      "ShortName": "FS_Dirt-008.wav",
      "CachePath": "SFX/FS_Dirt-008_10C4C929.wem"
     },
     {
      "Id": "89571094",
      "Language": "SFX",
      "Streaming": "false",
      "Location": "Memory",
      "ShortName": "FS_Dirt-002.wav",
      "CachePath": "SFX/FS_Dirt-002_6D629569.wem"
     },
     {
      "Id": "98455453",
      "Language": "SFX",
      "Streaming": "false",
      "Location": "Memory",
      "ShortName": "Goblin_Hit-003.wav",
      "CachePath": "SFX/Goblin_Hit-003_10C4C929.wem"
     },
     {
      "Id": "124337950",
      "Language": "SFX",
      "Streaming": "false",
      "Location": "Memory",
      "ShortName": "Goblin_HitGrunt-002.wav",
      "CachePath": "SFX/Goblin_HitGrunt-002_10C4C929.wem"
     },
     {
      "Id": "126572019",
      "Language": "SFX",
      "Streaming": "false",
      "Location": "Memory",
      "ShortName": "Fire_campfire_looped.wav",
      "CachePath": "SFX/Fire_campfire_looped_451D858D.wem"
     },
     {
      "Id": "127295719",
      "Language": "SFX",
      "Streaming": "false",
      "Location": "Memory",
      "ShortName": "FS_Dirt-006.wav",
      "CachePath": "SFX/FS_Dirt-006_10C4C929.wem"
     },
     {
      "Id": "132058878",
      "Language": "SFX",
      "Streaming": "false",
      "Location": "Memory",
      "ShortName": "GroundSlam-001.wav",
      "CachePath": "SFX/GroundSlam-001_10C4C929.wem"
     },
     {
      "Id": "145900662",
      "Language": "SFX",
      "Streaming": "false",
      "Location": "Memory",
      "ShortName": "FS_Stone-003.wav",
      "CachePath": "SFX/FS_Stone-003_10C4C929.wem"
     },
     {
      "Id": "150671417",
      "Language": "SFX",
      "Streaming": "false",
      "Location": "Memory",
      "ShortName": "Grunt-003.wav",
      "CachePath": "SFX/Grunt-003_10C4C929.wem"
     },
     {
      "Id": "154883674",
      "Language": "SFX",
      "Streaming": "false",
      "Location": "Memory",
      "ShortName": "DeathWhisle-005.wav",
      "CachePath": "SFX/DeathWhisle-005_10C4C929.wem"
     },
     {
      "Id": "159760995",
      "Language": "SFX",
      "Streaming": "false",
      "Location": "Memory",
      "ShortName": "DeathWhisle-009.wav",
      "CachePath": "SFX/DeathWhisle-009_10C4C929.wem"
     },
     {
      "Id": "160212660",
      "Language": "SFX",
      "Streaming": "false",
      "Location": "Memory",
      "ShortName": "GroundSlam-004.wav",
      "CachePath": "SFX/GroundSlam-004_10C4C929.wem"
     },
     {
      "Id": "177184956",
      "Language": "SFX",
      "Streaming": "false",
      "Location": "Memory",
      "ShortName": "Goblin_SwingGrunt-004.wav",
      "CachePath": "SFX/Goblin_SwingGrunt-004_10C4C929.wem"
     },
     {
      "Id": "189293494",
      "Language": "SFX",
      "Streaming": "false",
      "Location": "Memory",
      "ShortName": "DeathWhisle-004.wav",
      "CachePath": "SFX/DeathWhisle-004_10C4C929.wem"
     },
     {
      "Id": "204730486",
      "Language": "SFX",
      "Streaming": "false",
      "Location": "Memory",
      "ShortName": "FS_Dirt-009.wav",
      "CachePath": "SFX/FS_Dirt-009_10C4C929.wem"
     },
     {
      "Id": "214131361",
      "Language": "SFX",
      "Streaming": "false",
      "Location": "Memory",
      "ShortName": "Axe_Woosh-003.wav",
      "CachePath": "SFX/Axe_Woosh-003_200A8291.wem"
     },
     {
      "Id": "255433557",
      "Language": "SFX",
      "Streaming": "false",
      "Location": "Memory",
      "ShortName": "Grunt_Hit-002.wav",
      "CachePath": "SFX/Grunt_Hit-002_10C4C929.wem"
     },
     {
      "Id": "260312320",
      "Language": "SFX",
      "Streaming": "false",
      "Location": "Memory",
      "ShortName": "FS_Dirt-004.wav",
      "CachePath": "SFX/FS_Dirt-004_10C4C929.wem"
     },
     {
      "Id": "272739410",
      "Language": "SFX",
      "Streaming": "false",
      "Location": "Memory",
      "ShortName": "Goblin_SwingGrunt-005.wav",
      "CachePath": "SFX/Goblin_SwingGrunt-005_10C4C929.wem"
     },
     {
      "Id": "276472349",
      "Language": "SFX",
      "Streaming": "false",
      "Location": "Memory",
      "ShortName": "Grunt-002.wav",
      "CachePath": "SFX/Grunt-002_10C4C929.wem"
     },
     {
      "Id": "280510783",
      "Language": "SFX",
      "Streaming": "false",
      "Location": "Memory",
      "ShortName": "Grunt-004.wav",
      "CachePath": "SFX/Grunt-004_10C4C929.wem"
     },
     {
      "Id": "292023544",
      "Language": "SFX",
      "Streaming": "false",
      "Location": "Memory",
      "ShortName": "Roll-001.wav",
      "CachePath": "SFX/Roll-001_10C4C929.wem"
     },
     {
      "Id": "304137325",
      "Language": "SFX",
      "Streaming": "false",
      "Location": "Memory",
      "ShortName": "Goblin_SwingGrunt-003.wav",
      "CachePath": "SFX/Goblin_SwingGrunt-003_10C4C929.wem"
     },
     {
      "Id": "324544122",
      "Language": "SFX",
      "Streaming": "false",
      "Location": "Memory",
      "ShortName": "Goblin_Hit-004.wav",
      "CachePath": "SFX/Goblin_Hit-004_10C4C929.wem"
     },
     {
      "Id": "327556540",
      "Language": "SFX",
      "Streaming": "false",
      "Location": "Memory",
      "ShortName": "DeathWhisle-007.wav",
      "CachePath": "SFX/DeathWhisle-007_10C4C929.wem"
     },
     {
      "Id": "327704554",
      "Language": "SFX",
      "Streaming": "false",
      "Location": "Memory",
      "ShortName": "Roll-003.wav",
      "CachePath": "SFX/Roll-003_10C4C929.wem"
     },
     {
      "Id": "351961489",
      "Language": "SFX",
      "Streaming": "false",
      "Location": "Memory",
      "ShortName": "DeathWhisle-003.wav",
      "CachePath": "SFX/DeathWhisle-003_10C4C929.wem"
     },
     {
      "Id": "353512300",
      "Language": "SFX",
      "Streaming": "false",
      "Location": "Memory",
      "ShortName": "GroundSlam-003.wav",
      "CachePath": "SFX/GroundSlam-003_10C4C929.wem"
     },
     {
      "Id": "403653278",
      "Language": "SFX",
      "Streaming": "false",
      "Location": "Memory",
      "ShortName": "Soul.wav",
      "CachePath": "SFX/Soul_10C4C929.wem"
     },
     {
      "Id": "414051185",
      "Language": "SFX",
      "Streaming": "false",
      "Location": "Memory",
      "ShortName": "Goblin_SwingGrunt-001.wav",
      "CachePath": "SFX/Goblin_SwingGrunt-001_10C4C929.wem"
     },
     {
      "Id": "414075697",
      "Language": "SFX",
      "Streaming": "false",
      "Location": "Memory",
      "ShortName": "Goblin_HitGrunt-001.wav",
      "CachePath": "SFX/Goblin_HitGrunt-001_10C4C929.wem"
     },
     {
      "Id": "424450536",
      "Language": "SFX",
      "Streaming": "false",
      "Location": "Memory",
      "ShortName": "Roll-002.wav",
      "CachePath": "SFX/Roll-002_10C4C929.wem"
     },
     {
      "Id": "443029432",
      "Language": "SFX",
      "Streaming": "false",
      "Location": "Memory",
      "ShortName": "DeathWhisle-010.wav",
      "CachePath": "SFX/DeathWhisle-010_10C4C929.wem"
     },
     {
      "Id": "462682426",
      "Language": "SFX",
      "Streaming": "false",
      "Location": "Memory",
      "ShortName": "Water_Impact.wav",
      "CachePath": "SFX/Water_Impact_10C4C929.wem"
     },
     {
      "Id": "463423689",
      "Language": "SFX",
      "Streaming": "false",
      "Location": "Memory",
      "ShortName": "Fire_campfire_looped.wav",
      "CachePath": "SFX/Fire_campfire_looped_38EB4FBD.wem"
     },
     {
      "Id": "468771132",
      "Language": "SFX",
      "Streaming": "false",
      "Location": "Memory",
      "ShortName": "GroundSlam-002.wav",
      "CachePath": "SFX/GroundSlam-002_10C4C929.wem"
     },
     {
      "Id": "501518518",
      "Language": "SFX",
      "Streaming": "false",
      "Location": "Memory",
      "ShortName": "Fire_campfire_looped.wav",
      "CachePath": "SFX/Fire_campfire_looped_0AFC011F.wem"
     },
     {
      "Id": "515498122",
      "Language": "SFX",
      "Streaming": "false",
      "Location": "Memory",
      "ShortName": "FS_Sand-005.wav",
      "CachePath": "SFX/FS_Sand-005_975436C1.wem"
     },
     {
      "Id": "542846243",
      "Language": "SFX",
      "Streaming": "false",
      "Location": "Memory",
      "ShortName": "FS_Stone-002.wav",
      "CachePath": "SFX/FS_Stone-002_10C4C929.wem"
     },
     {
      "Id": "543332638",
      "Language": "SFX",
      "Streaming": "false",
      "Location": "Memory",
      "ShortName": "Goblin_HitGrunt-004.wav",
      "CachePath": "SFX/Goblin_HitGrunt-004_10C4C929.wem"
     },
     {
      "Id": "587868897",
      "Language": "SFX",
      "Streaming": "false",
      "Location": "Memory",
      "ShortName": "Rock_Impact_Tail.wav",
      "CachePath": "SFX/Rock_Impact_Tail_10C4C929.wem"
     },
     {
      "Id": "592633598",
      "Language": "SFX",
      "Streaming": "false",
      "Location": "Memory",
      "ShortName": "FS_Stone-001.wav",
      "CachePath": "SFX/FS_Stone-001_ADCE41BB.wem"
     },
     {
      "Id": "594466621",
      "Language": "SFX",
      "Streaming": "false",
      "Location": "Memory",
      "ShortName": "DeathWhisle-001.wav",
      "CachePath": "SFX/DeathWhisle-001_10C4C929.wem"
     },
     {
      "Id": "619938227",
      "Language": "SFX",
      "Streaming": "false",
      "Location": "Memory",
      "ShortName": "FS_Dirt-007.wav",
      "CachePath": "SFX/FS_Dirt-007_4E8974D4.wem"
     },
     {
      "Id": "621236505",
      "Language": "SFX",
      "Streaming": "false",
      "Location": "Memory",
      "ShortName": "FS_Sand-001.wav",
      "CachePath": "SFX/FS_Sand-001_10C4C929.wem"
     },
     {
      "Id": "631851801",
      "Language": "SFX",
      "Streaming": "false",
      "Location": "Memory",
      "ShortName": "Goblin_Hit-001.wav",
      "CachePath": "SFX/Goblin_Hit-001_10C4C929.wem"
     },
     {
      "Id": "655223332",
      "Language": "SFX",
      "Streaming": "false",
      "Location": "Memory",
      "ShortName": "Axe_Woosh-004.wav",
      "CachePath": "SFX/Axe_Woosh-004_7935DE21.wem"
     },
     {
      "Id": "662637876",
      "Language": "SFX",
      "Streaming": "false",
      "Location": "Memory",
      "ShortName": "DeathWhisle-002.wav",
      "CachePath": "SFX/DeathWhisle-002_10C4C929.wem"
     },
     {
      "Id": "683503367",
      "Language": "SFX",
      "Streaming": "false",
      "Location": "Memory",
      "ShortName": "Shot.wav",
      "CachePath": "SFX/Shot_A60E7EF7.wem"
     },
     {
      "Id": "724030898",
      "Language": "SFX",
      "Streaming": "false",
      "Location": "Memory",
      "ShortName": "Death_Cry.wav",
      "CachePath": "SFX/Death_Cry_10C4C929.wem"
     },
     {
      "Id": "724375867",
      "Language": "SFX",
      "Streaming": "false",
      "Location": "Memory",
      "ShortName": "FS_Stone-004.wav",
      "CachePath": "SFX/FS_Stone-004_160E022F.wem"
     },
     {
      "Id": "730473686",
      "Language": "SFX",
      "Streaming": "false",
      "Location": "Memory",
      "ShortName": "FS_Sand-003.wav",
      "CachePath": "SFX/FS_Sand-003_EE252982.wem"
     },
     {
      "Id": "739363478",
      "Language": "SFX",
      "Streaming": "false",
      "Location": "Memory",
      "ShortName": "Axe_Woosh-001.wav",
      "CachePath": "SFX/Axe_Woosh-001_60014CC6.wem"
     },
     {
      "Id": "758842263",
      "Language": "SFX",
      "Streaming": "false",
      "Location": "Memory",
      "ShortName": "FS_Stone-006.wav",
      "CachePath": "SFX/FS_Stone-006_10C4C929.wem"
     },
     {
      "Id": "762810824",
      "Language": "SFX",
      "Streaming": "false",
      "Location": "Memory",
      "ShortName": "DeathWhisle-008.wav",
      "CachePath": "SFX/DeathWhisle-008_10C4C929.wem"
     },
     {
      "Id": "767676742",
      "Language": "SFX",
      "Streaming": "false",
      "Location": "Memory",
      "ShortName": "FS_Sand-002.wav",
      "CachePath": "SFX/FS_Sand-002_0DCFD865.wem"
     },
     {
      "Id": "781763137",
      "Language": "SFX",
      "Streaming": "false",
      "Location": "Memory",
      "ShortName": "FS_Stone-005.wav",
      "CachePath": "SFX/FS_Stone-005_10C4C929.wem"
     },
     {
      "Id": "782509230",
      "Language": "SFX",
      "Streaming": "false",
      "Location": "Memory",
      "ShortName": "FS_Dirt-010.wav",
      "CachePath": "SFX/FS_Dirt-010_9FF36FA3.wem"
     },
     {
      "Id": "797124082",
      "Language": "SFX",
      "Streaming": "true",
      "Location": "Memory",
      "ShortName": "AMBDsgn_Aztec Death Whistle Designed Wind Drone_B00M_MBDW.wav",
      "Path": "Media/797124082.wem",
      "CachePath": "SFX/AMBDsgn_Aztec Death Whistle Designed Wind Drone_B00M_MBDW_C9E8E480.wem",
      "PrefetchSize": "8096"
     },
     {
      "Id": "802194300",
      "Language": "SFX",
      "Streaming": "false",
      "Location": "Memory",
      "ShortName": "Pickup_Item.wav",
      "CachePath": "SFX/Pickup_Item_10C4C929.wem"
     },
     {
      "Id": "822063392",
      "Language": "SFX",
      "Streaming": "false",
      "Location": "Memory",
      "ShortName": "Consume_Pot.wav",
      "CachePath": "SFX/Consume_Pot_10C4C929.wem"
     },
     {
      "Id": "849268683",
      "Language": "SFX",
      "Streaming": "false",
      "Location": "Memory",
      "ShortName": "DeathWhisle-006.wav",
      "CachePath": "SFX/DeathWhisle-006_10C4C929.wem"
     },
     {
      "Id": "852612398",
      "Language": "SFX",
      "Streaming": "false",
      "Location": "Memory",
      "ShortName": "Fire_campfire_looped.wav",
      "CachePath": "SFX/Fire_campfire_looped_F4C21E0C.wem"
     },
     {
      "Id": "867752228",
      "Language": "SFX",
      "Streaming": "false",
      "Location": "Memory",
      "ShortName": "Grunt_Hit-001.wav",
      "CachePath": "SFX/Grunt_Hit-001_10C4C929.wem"
     },
     {
      "Id": "876443643",
      "Language": "SFX",
      "Streaming": "false",
      "Location": "Memory",
      "ShortName": "FS_Sand-004.wav",
      "CachePath": "SFX/FS_Sand-004_AC4E9533.wem"
     },
     {
      "Id": "877945358",
      "Language": "SFX",
      "Streaming": "false",
      "Location": "Memory",
      "ShortName": "Fire_campfire_looped.wav",
      "CachePath": "SFX/Fire_campfire_looped_28A37B2F.wem"
     },
     {
      "Id": "878471934",
      "Language": "SFX",
      "Streaming": "false",
      "Location": "Memory",
      "ShortName": "Goblin_HitGrunt-003.wav",
      "CachePath": "SFX/Goblin_HitGrunt-003_10C4C929.wem"
     },
     {
      "Id": "900859556",
      "Language": "SFX",
      "Streaming": "false",
      "Location": "Memory",
      "ShortName": "Goblin_SwingGrunt-002.wav",
      "CachePath": "SFX/Goblin_SwingGrunt-002_10C4C929.wem"
     },
     {
      "Id": "902316126",
      "Language": "SFX",
      "Streaming": "false",
      "Location": "Memory",
      "ShortName": "Goblin_SwingGrunt-006.wav",
      "CachePath": "SFX/Goblin_SwingGrunt-006_10C4C929.wem"
     },
     {
      "Id": "916982560",
      "Language": "SFX",
      "Streaming": "false",
      "Location": "Memory",
      "ShortName": "FS_Dirt-005.wav",
      "CachePath": "SFX/FS_Dirt-005_10C4C929.wem"
     },
     {
      "Id": "924407592",
      "Language": "SFX",
      "Streaming": "false",
      "Location": "Memory",
      "ShortName": "Goblin_Hit-002.wav",
      "CachePath": "SFX/Goblin_Hit-002_10C4C929.wem"
     },
     {
      "Id": "964898346",
      "Language": "SFX",
      "Streaming": "false",
      "Location": "Memory",
      "ShortName": "Fire_campfire_looped.wav",
      "CachePath": "SFX/Fire_campfire_looped_177AA162.wem"
     },
     {
      "Id": "984305080",
      "Language": "SFX",
      "Streaming": "false",
      "Location": "Memory",
      "ShortName": "FS_Dirt-001.wav",
      "CachePath": "SFX/FS_Dirt-001_10C4C929.wem"
     },
     {
      "Id": "1029893350",
      "Language": "SFX",
      "Streaming": "false",
      "Location": "Memory",
      "ShortName": "Axe_Woosh-002.wav",
      "CachePath": "SFX/Axe_Woosh-002_561844A0.wem"
     },
     {
      "Id": "1030431893",
      "Language": "SFX",
      "Streaming": "false",
      "Location": "Memory",
      "ShortName": "Fire_campfire_looped.wav",
      "CachePath": "SFX/Fire_campfire_looped_7A9B7E06.wem"
     },
     {
      "Id": "1033455963",
      "Language": "SFX",
      "Streaming": "false",
      "Location": "Memory",
      "ShortName": "Roll-004.wav",
      "CachePath": "SFX/Roll-004_10C4C929.wem"
     },
     {
      "Id": "1072310648",
      "Language": "SFX",
      "Streaming": "false",
      "Location": "Memory",
      "ShortName": "Grunt-001.wav",
      "CachePath": "SFX/Grunt-001_10C4C929.wem"
     }
    ],
    "Plugins": {
     "Custom": [
      {
       "Id": "257343408",
       "Name": "Silence",
       "ObjectPath": "\\Actor-Mixer Hierarchy\\Default Work Unit\\Player\\Grunt_Swing\\None-001\\Silence",
       "GUID": "{597F46D7-0A3C-4B47-8F27-6ED1FA5A1ED7}",
       "LibName": "Wwise Silence",
       "LibId": "6619138"
      },
      {
       "Id": "518936202",
       "Name": "Silence",
       "ObjectPath": "\\Actor-Mixer Hierarchy\\Default Work Unit\\Player\\Grunt_Swing\\None-002\\Silence",
       "GUID": "{F637D481-18E6-4CDF-916B-B6BCBED76C32}",
       "LibName": "Wwise Silence",
       "LibId": "6619138"
      },
      {
       "Id": "769512910",
       "Name": "Silence",
       "ObjectPath": "\\Actor-Mixer Hierarchy\\Default Work Unit\\Goblin\\Goblin_HitGrunt\\New Sound SFX_01\\Silence",
       "GUID": "{1A638881-209D-443B-AA28-2E394F799449}",
       "LibName": "Wwise Silence",
       "LibId": "6619138"
      },
      {
       "Id": "930266521",
       "Name": "Silence",
       "ObjectPath": "\\Actor-Mixer Hierarchy\\Default Work Unit\\Goblin\\Goblin_HitGrunt\\New Sound SFX\\Silence",
       "GUID": "{C8FC8F3F-7462-4786-8A8A-4C53BFB9DDF8}",
       "LibName": "Wwise Silence",
       "LibId": "6619138"
      }
     ]
    },
    "Events": [
     {
      "Id": "4000411161",
      "Name": "Play_Campfire",
      "ObjectPath": "\\Events\\Default Work Unit\\Play_Campfire",
      "GUID": "{B5E84B6B-D27A-47DE-8110-AB244A8386AB}",
      "MaxAttenuation": "1350",
      "DurationType": "OneShot",
      "DurationMin": "102.32407",
      "DurationMax": "102.32407",
      "MediaRefs": [
       {
        "Id": "126572019"
       },
       {
        "Id": "463423689"
       },
       {
        "Id": "501518518"
       },
       {
        "Id": "852612398"
       },
       {
        "Id": "877945358"
       },
       {
        "Id": "964898346"
       },
       {
        "Id": "1030431893"
       }
      ]
     },
     {
      "Id": "3442516748",
      "Name": "Play_Consume_Pot",
      "ObjectPath": "\\Events\\Default Work Unit\\Play_Consume_Pot",
      "GUID": "{4350D16C-4077-4664-84DC-590102EF49CC}",
      "DurationType": "OneShot",
      "DurationMin": "1.5935833",
      "DurationMax": "1.5935833",
      "MediaRefs": [
       {
        "Id": "822063392"
       }
      ]
     },
     {
      "Id": "2495770949",
      "Name": "Play_Death_Cry",
      "ObjectPath": "\\Events\\Default Work Unit\\Play_Death_Cry",
      "GUID": "{73C1D3B6-84DF-4834-8FB2-67BA65816D2D}",
      "DurationType": "OneShot",
      "DurationMin": "5.3",
      "DurationMax": "5.3",
      "MediaRefs": [
       {
        "Id": "724030898"
       }
      ]
     },
     {
      "Id": "1661060282",
      "Name": "Play_DeathWhisleLow",
      "ObjectPath": "\\Events\\Default Work Unit\\Play_DeathWhisleLow",
      "GUID": "{E2583857-8048-48ED-AB46-406606089EAF}",
      "DurationType": "OneShot",
      "DurationMin": "154.03534",
      "DurationMax": "154.03534",
      "MediaRefs": [
       {
        "Id": "797124082"
       }
      ]
     },
     {
      "Id": "3854155799",
      "Name": "Play_Footsteps",
      "ObjectPath": "\\Events\\Default Work Unit\\Play_Footsteps",
      "GUID": "{F60C7D25-F5E7-44EC-BE4C-3BC28FC88BC2}",
      "DurationType": "OneShot",
      "DurationMin": "0",
      "DurationMax": "0.43254086",
      "SwitchContainers": [
       {
        "SwitchValue": {
         "GroupType": "Switch",
         "GroupId": "1834394558",
         "Id": "803837735",
         "GUID": "{07261111-85DA-4848-9D5C-4590F83E2574}"
        },
        "MediaRefs": [
         {
          "Id": "515498122"
         },
         {
          "Id": "621236505"
         },
         {
          "Id": "730473686"
         },
         {
          "Id": "767676742"
         },
         {
          "Id": "876443643"
         }
        ]
       },
       {
        "SwitchValue": {
         "GroupType": "Switch",
         "GroupId": "1834394558",
         "Id": "1216965916",
         "GUID": "{81127D2F-33FA-4645-B673-AAE14C0A3834}"
        },
        "MediaRefs": [
         {
          "Id": "145900662"
         },
         {
          "Id": "542846243"
         },
         {
          "Id": "592633598"
         },
         {
          "Id": "724375867"
         },
         {
          "Id": "758842263"
         },
         {
          "Id": "781763137"
         }
        ]
       },
       {
        "SwitchValue": {
         "GroupType": "Switch",
         "GroupId": "1834394558",
         "Id": "2195636714",
         "GUID": "{99AE1BB1-0840-4DA3-8906-184B4A011CBE}",
         "Default": "true"
        },
        "MediaRefs": [
         {
          "Id": "33923621"
         },
         {
          "Id": "75816713"
         },
         {
          "Id": "89571094"
         },
         {
          "Id": "127295719"
         },
         {
          "Id": "204730486"
         },
         {
          "Id": "260312320"
         },
         {
          "Id": "619938227"
         },
         {
          "Id": "782509230"
         },
         {
          "Id": "916982560"
         },
         {
          "Id": "984305080"
         }
        ]
       }
      ]
     },
     {
      "Id": "76150229",
      "Name": "Play_Goblin_Hit",
      "ObjectPath": "\\Events\\Default Work Unit\\Play_Goblin_Hit",
      "GUID": "{88D2793B-0B11-4B43-9418-705193C74F91}",
      "DurationType": "OneShot",
      "DurationMin": "0.35871154",
      "DurationMax": "1.122462",
      "MediaRefs": [
       {
        "Id": "98455453"
       },
       {
        "Id": "124337950"
       },
       {
        "Id": "324544122"
       },
       {
        "Id": "414075697"
       },
       {
        "Id": "543332638"
       },
       {
        "Id": "631851801"
       },
       {
        "Id": "878471934"
       },
       {
        "Id": "924407592"
       }
      ],
      "PluginRefs": {
       "Custom": [
        {
         "Id": "769512910"
        },
        {
         "Id": "930266521"
        }
       ]
      }
     },
     {
      "Id": "2355713830",
      "Name": "Play_Goblin_SwingGrunt",
      "ObjectPath": "\\Events\\Default Work Unit\\Play_Goblin_SwingGrunt",
      "GUID": "{2E89F717-9215-43A4-ADA0-EC4D34E498A0}",
      "DurationType": "OneShot",
      "DurationMin": "0.16810793",
      "DurationMax": "0.59272546",
      "MediaRefs": [
       {
        "Id": "177184956"
       },
       {
        "Id": "272739410"
       },
       {
        "Id": "304137325"
       },
       {
        "Id": "414051185"
       },
       {
        "Id": "900859556"
       },
       {
        "Id": "902316126"
       }
      ]
     },
     {
      "Id": "1055240968",
      "Name": "Play_GroundSlam",
      "ObjectPath": "\\Events\\Default Work Unit\\Play_GroundSlam",
      "GUID": "{156CA5F1-0D54-4975-AF58-D2814988E804}",
      "DurationType": "OneShot",
      "DurationMin": "3.345854",
      "DurationMax": "3.345854",
      "MediaRefs": [
       {
        "Id": "132058878"
       },
       {
        "Id": "160212660"
       },
       {
        "Id": "353512300"
       },
       {
        "Id": "468771132"
       }
      ],
      "SwitchContainers": [
       {
        "SwitchValue": {
         "GroupType": "Switch",
         "GroupId": "3257506471",
         "Id": "2195636714",
         "GUID": "{D63A2816-2BF5-4E43-96BF-92ADF5EFD709}",
         "Default": "true"
        },
        "MediaRefs": [
         {
          "Id": "31203274"
         }
        ]
       },
       {
        "SwitchValue": {
         "GroupType": "Switch",
         "GroupId": "3257506471",
         "Id": "2654748154",
         "GUID": "{76A15951-554F-417A-B26F-034713D0CAB1}"
        },
        "MediaRefs": [
         {
          "Id": "462682426"
         }
        ]
       },
       {
        "SwitchValue": {
         "GroupType": "Switch",
         "GroupId": "3257506471",
         "Id": "1216965916",
         "GUID": "{21EFE8C6-1AF6-4D9A-8F2C-D46DBAAC54F8}"
        },
        "MediaRefs": [
         {
          "Id": "31203274"
         }
        ]
       },
       {
        "SwitchValue": {
         "GroupType": "Switch",
         "GroupId": "3257506471",
         "Id": "2195636714",
         "GUID": "{D63A2816-2BF5-4E43-96BF-92ADF5EFD709}",
         "Default": "true"
        },
        "MediaRefs": [
         {
          "Id": "587868897"
         }
        ]
       },
       {
        "SwitchValue": {
         "GroupType": "Switch",
         "GroupId": "3257506471",
         "Id": "1216965916",
         "GUID": "{21EFE8C6-1AF6-4D9A-8F2C-D46DBAAC54F8}"
        },
        "MediaRefs": [
         {
          "Id": "587868897"
         }
        ]
       }
      ]
     },
     {
      "Id": "2989619110",
      "Name": "Play_Grunt_Hit",
      "ObjectPath": "\\Events\\Default Work Unit\\Play_Grunt_Hit",
      "GUID": "{37E88AAD-7729-4CB0-BB5D-F4390FA81F32}",
      "DurationType": "OneShot",
      "DurationMin": "0.46309766",
      "DurationMax": "0.6789569",
      "MediaRefs": [
       {
        "Id": "13622979"
       },
       {
        "Id": "255433557"
       },
       {
        "Id": "867752228"
       }
      ]
     },
     {
      "Id": "390202731",
      "Name": "Play_Grunt_Swing",
      "ObjectPath": "\\Events\\Default Work Unit\\Play_Grunt_Swing",
      "GUID": "{370F6A5C-2EF0-4E9B-92B4-58522F85F30B}",
      "DurationType": "OneShot",
      "DurationMin": "0.32939285",
      "DurationMax": "1.0594631",
      "MediaRefs": [
       {
        "Id": "150671417"
       },
       {
        "Id": "276472349"
       },
       {
        "Id": "280510783"
       },
       {
        "Id": "1072310648"
       }
      ],
      "PluginRefs": {
       "Custom": [
        {
         "Id": "257343408"
        },
        {
         "Id": "518936202"
        }
       ]
      }
     },
     {
      "Id": "3128913152",
      "Name": "Play_Pickup_Item",
      "ObjectPath": "\\Events\\Default Work Unit\\Play_Pickup_Item",
      "GUID": "{1BF7DE81-21DD-4880-9D2B-651089A08519}",
      "DurationType": "OneShot",
      "DurationMin": "0.9350279",
      "DurationMax": "0.9906275",
      "MediaRefs": [
       {
        "Id": "802194300"
       }
      ]
     },
     {
      "Id": "876482232",
      "Name": "Play_Pickup_Soul",
      "ObjectPath": "\\Events\\Default Work Unit\\Play_Pickup_Soul",
      "GUID": "{E98FAC64-537B-4345-8875-2012A4F0FFD4}",
      "DurationType": "OneShot",
      "DurationMin": "0.81188715",
      "DurationMax": "1.2164563",
      "MediaRefs": [
       {
        "Id": "403653278"
       }
      ]
     },
     {
      "Id": "2517823277",
      "Name": "Play_PlayerSwing",
      "ObjectPath": "\\Events\\Default Work Unit\\Play_PlayerSwing",
      "GUID": "{AFA713F3-4D2D-4FBC-AC0E-B6907EA6D895}",
      "DurationType": "OneShot",
      "DurationMin": "0.76057065",
      "DurationMax": "0.91239566",
      "MediaRefs": [
       {
        "Id": "214131361"
       },
       {
        "Id": "655223332"
       },
       {
        "Id": "739363478"
       },
       {
        "Id": "1029893350"
       }
      ]
     },
     {
      "Id": "832213799",
      "Name": "Play_RandomDeathWhisle",
      "ObjectPath": "\\Events\\Default Work Unit\\Play_RandomDeathWhisle",
      "GUID": "{BCEDE4E9-3AF8-47C6-83F2-8964D204FB00}",
      "MaxAttenuation": "1400",
      "DurationType": "Infinite",
      "MediaRefs": [
       {
        "Id": "154883674"
       },
       {
        "Id": "159760995"
       },
       {
        "Id": "189293494"
       },
       {
        "Id": "327556540"
       },
       {
        "Id": "351961489"
       },
       {
        "Id": "443029432"
       },
       {
        "Id": "594466621"
       },
       {
        "Id": "662637876"
       },
       {
        "Id": "762810824"
       },
       {
        "Id": "849268683"
       }
      ],
      "AuxBusRefs": [
       {
        "Id": "4263088964",
        "Name": "DeathWhisle_Reverb",
        "ObjectPath": "\\Master-Mixer Hierarchy\\Default Work Unit\\Master Audio Bus\\Gameplay\\DeathWhisle_Reverb",
        "GUID": "{2355226F-E4CB-4F1D-AB37-7842C4BAD5C0}"
       }
      ]
     },
     {
      "Id": "2719919427",
      "Name": "Play_Roll",
      "ObjectPath": "\\Events\\Default Work Unit\\Play_Roll",
      "GUID": "{15BD5FA2-3632-4298-AF18-6DE42A2CC5EE}",
      "DurationType": "OneShot",
      "DurationMin": "0.46247873",
      "DurationMax": "0.57222044",
      "MediaRefs": [
       {
        "Id": "292023544"
       },
       {
        "Id": "327704554"
       },
       {
        "Id": "424450536"
       },
       {
        "Id": "1033455963"
       }
      ]
     },
     {
      "Id": "3187507146",
      "Name": "Play_Test",
      "ObjectPath": "\\Events\\Default Work Unit\\Play_Test",
      "GUID": "{72C814D5-F2EE-4A26-9D04-DCB4C83E7589}",
      "DurationType": "OneShot",
      "DurationMin": "0.9964848",
      "DurationMax": "0.9964848",
      "MediaRefs": [
       {
        "Id": "683503367"
       }
      ],
      "AuxBusRefs": [
       {
        "Id": "3717191513",
        "Name": "OpenCave_Reverb",
        "ObjectPath": "\\Master-Mixer Hierarchy\\Default Work Unit\\Master Audio Bus\\Gameplay\\OpenCave_Reverb",
        "GUID": "{6C93671D-1FB3-4167-8C0E-D3BA1142FA69}"
       }
      ]
     }
    ],
    "SwitchGroups": [
     {
      "Id": "1834394558",
      "Name": "Surface",
      "ObjectPath": "\\Switches\\Default Work Unit\\Surface",
      "GUID": "{DAA0AC4F-CD6C-4725-9736-F10D4275C9F1}",
      "Switches": [
       {
        "Id": "712897245",
        "Name": "Mud",
        "ObjectPath": "\\Switches\\Default Work Unit\\Surface\\Mud",
        "GUID": "{F56F098E-C950-4E09-9E48-305F3D9917D2}"
       },
       {
        "Id": "803837735",
        "Name": "Sand",
        "ObjectPath": "\\Switches\\Default Work Unit\\Surface\\Sand",
        "GUID": "{07261111-85DA-4848-9D5C-4590F83E2574}"
       },
       {
        "Id": "1216965916",
        "Name": "Stone",
        "ObjectPath": "\\Switches\\Default Work Unit\\Surface\\Stone",
        "GUID": "{81127D2F-33FA-4645-B673-AAE14C0A3834}"
       },
       {
        "Id": "2195636714",
        "Name": "Dirt",
        "ObjectPath": "\\Switches\\Default Work Unit\\Surface\\Dirt",
        "GUID": "{99AE1BB1-0840-4DA3-8906-184B4A011CBE}"
       },
       {
        "Id": "2654748154",
        "Name": "Water",
        "ObjectPath": "\\Switches\\Default Work Unit\\Surface\\Water",
        "GUID": "{B9EA5374-CA9F-4D4B-A504-D33B42796948}"
       }
      ]
     },
     {
      "Id": "3257506471",
      "Name": "Impact",
      "ObjectPath": "\\Switches\\Default Work Unit\\Impact",
      "GUID": "{F15315EE-20B4-4E71-A6F0-2E2ECBEA8B7A}",
      "Switches": [
       {
        "Id": "1216965916",
        "Name": "Stone",
        "ObjectPath": "\\Switches\\Default Work Unit\\Impact\\Stone",
        "GUID": "{21EFE8C6-1AF6-4D9A-8F2C-D46DBAAC54F8}"
       },
       {
        "Id": "2195636714",
        "Name": "Dirt",
        "ObjectPath": "\\Switches\\Default Work Unit\\Impact\\Dirt",
        "GUID": "{D63A2816-2BF5-4E43-96BF-92ADF5EFD709}"
       },
       {
        "Id": "2654748154",
        "Name": "Water",
        "ObjectPath": "\\Switches\\Default Work Unit\\Impact\\Water",
        "GUID": "{76A15951-554F-417A-B26F-034713D0CAB1}"
       }
      ]
     }
    ]
   }
  ],
  "FileHash": "{783E5DA1-2429-39A5-B2B0-A606D3498455}"
 }
}